gcMapExplorer/main.py
gcMapExplorer/__init__.py
gcMapExplorer/config.py
gcMapExplorer/_version.py
gcMapExplorer/.libs/libgomp-3d5ea87c.so.1.0.0
gcMapExplorer/lib/hicparser.py
gcMapExplorer/lib/normalizeCore.cpython-34m.so
gcMapExplorer/lib/hic2gcmap.py
gcMapExplorer/lib/ccmap.py
gcMapExplorer/lib/ccmapHelpers.c
gcMapExplorer/lib/importer.py
gcMapExplorer/lib/genomicsDataHandler.py
gcMapExplorer/lib/normalizeCore.c
gcMapExplorer/lib/normalizeKnightRuiz.cpython-34m.so
gcMapExplorer/lib/normalizeCore.pyx
gcMapExplorer/lib/statDist.py
gcMapExplorer/lib/gcmap.py
gcMapExplorer/lib/normalizer.py
gcMapExplorer/lib/_corrMatrixCore.cpython-34m.so
gcMapExplorer/lib/TadFinder.c
gcMapExplorer/lib/__init__.py
gcMapExplorer/lib/normalizeKnightRuiz.pyx
gcMapExplorer/lib/corrMatrixCoreSRC.h
gcMapExplorer/lib/TadFinder.cpython-34m.so
gcMapExplorer/lib/TadFinder.pyx
gcMapExplorer/lib/_corrMatrixCore.pyx
gcMapExplorer/lib/cmstats.py
gcMapExplorer/lib/corrMatrix.py
gcMapExplorer/lib/normalizeKnightRuiz.c
gcMapExplorer/lib/compartments.py
gcMapExplorer/lib/ccmapHelpers.pyx
gcMapExplorer/lib/util.py
gcMapExplorer/lib/ccmapHelpers.cpython-34m.so
gcMapExplorer/lib/corrMatrixCoreSRC.c
gcMapExplorer/gui/browser.py
gcMapExplorer/gui/h5Converter.py
gcMapExplorer/gui/normalizer_ui.py
gcMapExplorer/gui/__init__.py
gcMapExplorer/gui/guiHelpers.py
gcMapExplorer/gui/importer_ui.py
gcMapExplorer/gui/browserHelpers.py
gcMapExplorer/gui/UIs/textFileSelector.ui
gcMapExplorer/gui/UIs/gcmapSelectorForBrowser.ui
gcMapExplorer/gui/UIs/importer.ui
gcMapExplorer/gui/UIs/aboutBrowser.ui
gcMapExplorer/gui/UIs/mainWindow.ui
gcMapExplorer/gui/UIs/mainWindow_old.ui
gcMapExplorer/gui/UIs/correlationMaps.ui
gcMapExplorer/gui/UIs/normalizer.ui
gcMapExplorer/gui/UIs/dialogAxisProps.ui
gcMapExplorer/gui/UIs/userColorMapDialog.ui
gcMapExplorer/gui/UIs/dialogCustomPageSize.ui
gcMapExplorer/gui/UIs/other1DFormatFileConversion.ui
gcMapExplorer-1.0.30.dist-info/WHEEL
gcMapExplorer-1.0.30.dist-info/top_level.txt
gcMapExplorer-1.0.30.dist-info/METADATA
gcMapExplorer-1.0.30.dist-info/RECORD
gcMapExplorer-1.0.30.dist-info/entry_points.txt
