Metadata-Version: 2.1
Name: gcMapExplorer
Version: 1.0.30
Summary: A platform to visualize and analyze genome contact maps
Home-page: https://github.com/rjdkmr/gcMapExplorer
Author: Rajendra Kumar
Author-email: rjdkmr@gmail.com
License: GNU General Public License v3 (GPLv3)
Keywords: Hi-C,Genome Contact Map Explorer,Contact Map Explorer,3D Genome Organization
Platform: UNKNOWN
Classifier: Environment :: Console
Classifier: Environment :: X11 Applications :: Qt
Classifier: Intended Audience :: Developers
Classifier: Intended Audience :: End Users/Desktop
Classifier: Intended Audience :: Science/Research
Classifier: License :: OSI Approved :: GNU General Public License v3 (GPLv3)
Classifier: Natural Language :: English
Classifier: Operating System :: MacOS
Classifier: Operating System :: Microsoft :: Windows
Classifier: Operating System :: POSIX :: Linux
Classifier: Programming Language :: Python :: 3 :: Only
Classifier: Topic :: Scientific/Engineering :: Bio-Informatics
Requires-Dist: appdirs (>=1.4)
Requires-Dist: numpy (>=1.6)
Requires-Dist: scipy (>=0.9)
Requires-Dist: matplotlib (>=1.1.0)
Requires-Dist: dask (>=0.7.3)
Requires-Dist: toolz (>=0.7.4)
Requires-Dist: psutil (>=5.2.0)
Requires-Dist: h5py (>=2.2.1)
Requires-Dist: Cython (>=0.23.0)
Requires-Dist: scikit-learn (>=0.19.0)
